openllm/__init__.py
openllm/__main__.py
openllm/_version.py
openllm/accelerator_spec.py
openllm/analytic.py
openllm/clean.py
openllm/cloud.py
openllm/common.py
openllm/local.py
openllm/model.py
openllm/py.typed
openllm/repo.py
openllm/venv.py
openllm-0.6.29.dist-info/METADATA
openllm-0.6.29.dist-info/WHEEL
openllm-0.6.29.dist-info/entry_points.txt
openllm-0.6.29.dist-info/licenses/LICENSE
openllm-0.6.29.dist-info/RECORD
