Metadata-Version: 2.4
Name: openllm
Version: 0.6.29
Summary: OpenLLM: Self-hosting LLMs Made Easy.
Project-URL: Blog, https://modelserving.com
Project-URL: Documentation, https://github.com/bentoml/OpenLLM#readme
Project-URL: GitHub, https://github.com/bentoml/OpenLLM
Project-URL: Homepage, https://bentoml.com
Project-URL: Tracker, https://github.com/bentoml/OpenLLM/issues
Project-URL: Twitter, https://twitter.com/bentomlai
Author-email: BentoML Team <contact@bentoml.com>
License-Expression: Apache-2.0
License-File: LICENSE
Keywords: AI,Alpaca,BentoML,Falcon,Fine tuning,Generative AI,LLMOps,Large Language Model,Llama 2,MLOps,Mistral,Model Deployment,Model Serving,PyTorch,Serverless,StableLM,Transformers,Vicuna,vLLM
Classifier: Development Status :: 5 - Production/Stable
Classifier: Environment :: GPU :: NVIDIA CUDA
Classifier: Environment :: GPU :: NVIDIA CUDA :: 11.7
Classifier: Environment :: GPU :: NVIDIA CUDA :: 11.8
Classifier: Environment :: GPU :: NVIDIA CUDA :: 12
Classifier: Intended Audience :: Developers
Classifier: Intended Audience :: Science/Research
Classifier: Intended Audience :: System Administrators
Classifier: License :: OSI Approved :: Apache Software License
Classifier: Operating System :: OS Independent
Classifier: Programming Language :: Python
Classifier: Programming Language :: Python :: 3
Classifier: Programming Language :: Python :: 3 :: Only
Classifier: Programming Language :: Python :: 3.8
Classifier: Programming Language :: Python :: 3.9
Classifier: Programming Language :: Python :: 3.10
Classifier: Programming Language :: Python :: 3.11
Classifier: Programming Language :: Python :: 3.12
Classifier: Programming Language :: Python :: Implementation :: CPython
Classifier: Programming Language :: Python :: Implementation :: PyPy
Classifier: Topic :: Scientific/Engineering :: Artificial Intelligence
Classifier: Topic :: Software Development :: Libraries
Classifier: Typing :: Typed
Requires-Python: >=3.9
Requires-Dist: bentoml==1.4.8
Requires-Dist: dulwich
Requires-Dist: hf-xet
Requires-Dist: huggingface-hub
Requires-Dist: nvidia-ml-py
Requires-Dist: openai==1.73.0
Requires-Dist: pathlib
Requires-Dist: pip-requirements-parser
Requires-Dist: psutil
Requires-Dist: pyaml
Requires-Dist: questionary
Requires-Dist: tabulate
Requires-Dist: typer
Requires-Dist: typing-extensions>=4.12.2
Requires-Dist: uv
